helloTestSecond-0.0.6.dist-info/DESCRIPTION.rst
helloTestSecond-0.0.6.dist-info/METADATA
helloTestSecond-0.0.6.dist-info/RECORD
helloTestSecond-0.0.6.dist-info/WHEEL
helloTestSecond-0.0.6.dist-info/metadata.json
helloTestSecond-0.0.6.dist-info/top_level.txt
libname/__init__.py
libname/hello.py
